{
  "type": "minecraft:entity",
  "pools": [
    {
      "rolls": 1,
      "_comment_chance": "TESTING VALUE — set to 1.0 (100%) to verify the drop pipeline works. Lower to 0.025–0.10 once confirmed.",
      "conditions": [
        {
          "condition": "minecraft:random_chance",
          "chance": 1.0
        }
      ],
      "entries": [
        {
          "type": "minecraft:item",
          "name": "supplementaries:quiver",
          "functions": [
            {
              "function": "supplementaries:random_arrows",
              "min": 4,
              "max": 18
            }
          ]
        }
      ]
    }
  ]
}
